gflags-stubs/METADATA.toml
gflags-stubs/__init__.pyi
gflags-stubs/py.typed
types_python_gflags-3.1.7.20241205.dist-info/LICENSE
types_python_gflags-3.1.7.20241205.dist-info/METADATA
types_python_gflags-3.1.7.20241205.dist-info/WHEEL
types_python_gflags-3.1.7.20241205.dist-info/top_level.txt
types_python_gflags-3.1.7.20241205.dist-info/RECORD
